tropicpy/__init__.py
tropicpy/tropicpy.py
tropicpy/attacks/attacks_utils.py
tropicpy/attacks/isaac_kahrobaei.py
tropicpy/attacks/kotov_ushakov.py
tropicpy/attacks/kotov_ushakov_simple.py
tropicpy/attacks/rudy_monico.py
tropicpy/protocols/grigorie_shpilrain_2014.py
tropicpy/protocols/grigorie_shpilrain_2019.py
tropicpy/tropical/tropical_matrix.py
tropicpy/tropical/tropical_utils.py
tropicpy/tropical/tropical_value.py
tropicpy-1.1.0.dist-info/LICENSE
tropicpy-1.1.0.dist-info/METADATA
tropicpy-1.1.0.dist-info/WHEEL
tropicpy-1.1.0.dist-info/top_level.txt
tropicpy-1.1.0.dist-info/RECORD
