Metadata-Version: 2.1
Name: tropicpy
Version: 1.1.0
Summary: Implementation of tropical cryptographic protocols and attacks.
Author-email: Marta Brzezinska <marta0brzezinska@gmail.com>
Project-URL: Homepage, https://github.com/marta0brzezinska/tropicpy
Classifier: Programming Language :: Python :: 3
Classifier: License :: OSI Approved :: GNU General Public License v3 (GPLv3)
Classifier: Operating System :: OS Independent
Requires-Python: >=3.8
License-File: LICENSE
